Workbook

Sheet README
A1: Stablecoins vs SWIFT — financial model (Oct 2026)
A3: How to use: change BLUE cells (yellow = key levers) on the Inputs sheet. Everything else is a formula.
A4: Colour code: blue = hardcoded input · black = formula · green = link to another sheet.
A6: Sheets:
A7: Inputs — every assumption, with its source or a note that it is an assumption.
A8: Corridors — 35 World Bank corridors: cheapest / median / average incumbent price vs the stablecoin rail cost.
A9: Pakistan — tests PVARA's Aug-2026 '$400m saving' claim against three benchmarks.
A10: Issuer P&L — Circle-style issuer economics and the 'rate-cut squeeze' (what 25–150bp of cuts does).
A11: Issuer Sensitivity — EBITDA grid: average supply × reserve yield.
A12: Corridor Product — 5-year P&L and NPV of a Saudi → South Asia stablecoin remittance product.
A14: Data vintages: stablecoin supply Oct 2026 (DefiLlama) · T-bill Sep 2026 (FRED) · Circle Q2 2026 results ·
A15: remittance prices Q3 2025 (latest World Bank release) · Pakistan flows FY26 (SBP).
A16: Not investment advice. Assumptions are illustrative and labelled.

Sheet Inputs
A1: Input | B1: Value | C1: Source / note
A2: Stablecoin rail — on-ramp cost (% of transfer) | B2: 0.005 | C2: ASSUMPTION: fiat→USD stablecoin at a licensed Gulf exchange/partner. Low case 0.1%, high 1.5%.
A3: Stablecoin rail — off-ramp cost incl. FX spread (%) | B3: 0.01 | C3: ASSUMPTION: stablecoin→local currency via licensed partner. Low 0.3%, high 3%.
A4: Stablecoin rail — fixed cost per transfer ($) | B4: 0.55 | C4: ASSUMPTION: network fee (~$0.05 on Solana/Base) + compliance/ops (~$0.50).
A5: Benchmark transfer size ($) | B5: 200 | C5: World Bank RPW benchmark ticket.
A6: USDC average circulation ($bn) | B6: 73 | C6: Circle Q2 2026: USDC $73.3bn end-period; DefiLlama Oct 2026 $72.7bn.
A7: Reserve yield (current, %) | B7: 0.0394 | C7: FRED TB3MS, Sep 2026 = 3.94%.
A8: Distribution & transaction costs as % of total revenue | B8: 0.605 | C8: Circle FY2025: $1,662m / $2,747m = 60.5%.
A9: Other revenue ($m / yr) | B9: 160 | C9: Circle FY2026 guidance $150–170m (midpoint).
A10: Adjusted operating expenses ($m / yr) | B10: 578 | C10: Circle FY2026 guidance $570–585m (midpoint).
A11: Payments take rate (bp of volume) | B11: 0.001 | C11: ASSUMPTION: 10bp, used to size payment volume needed to replace lost float income.
A12: Pakistan inflows from Saudi Arabia ($bn, FY26) | B12: 9.78 | C12: SBP via Gulf News, Jul 2026.
A13: Pakistan inflows from UAE ($bn, FY26) | B13: 8.81 | C13: SBP via Gulf News, Jul 2026.
... A24: Product — discount rate | B24: 0.18 | C24: ASSUMPTION: venture-stage emerging-market rate.
A26: Derived: stablecoin rail all-in cost on benchmark ticket | B26: =Inputs!$B$2+Inputs!$B$3+Inputs!$B$4/Inputs!$B$5 -> 0.01775

Sheet Corridors
A1: Corridor | B1: From | C1: To | D1: # offers | E1: Cheapest offer % | F1: Median offer % | G1: Average % | H1: Rail cost % | I1: Rail beats cheapest? | J1: Headroom vs cheapest (pp) | K1: Headroom vs median (pp)
A2: AE/PK | B2: UAE | C2: Pakistan | D2: 17 | E2: -0.0049 | F2: 0.0063 | G2: 0.0217 | H2: =Inputs!$B$26 -> 0.01775 | I2: =IF(E2>H2,"YES","no") -> no | J2: =(E2-H2)*100 -> -2.265 | K2: =(F2-H2)*100 -> -1.145
A3: SA/PK | B3: Saudi Arabia | C3: Pakistan | D3: 12 | E3: 0.0144 | F3: 0.0306 | G3: 0.0502 | H3: =Inputs!$B$26 -> 0.01775 | I3: =IF(E3>H3,"YES","no") -> no | J3: =(E3-H3)*100 -> -0.335 | K3: =(F3-H3)*100 -> 1.285
A4: GB/PK | B4: UK | C4: Pakistan | D4: 29 | E4: -0.0144 | F4: 0.0251 | G4: 0.0239 | H4: =Inputs!$B$26 -> 0.01775 | I4: =IF(E4>H4,"YES","no") -> no | J4: =(E4-H4)*100 -> -3.215 | K4: =(F4-H4)*100 -> 0.735
A5: US/PK | B5: USA | C5: Pakistan | D5: 25 | E5: 0.0045 | F5: 0.0263 | G5: 0.0381 | H5: =Inputs!$B$26 -> 0.01775 | I5: =IF(E5>H5,"YES","no") -> no | J5: =(E5-H5)*100 -> -1.325 | K5: =(F5-H5)*100 -> 0.855
A6: AE/IN | B6: UAE | C6: India | D6: 24 | E6: 0.0077 | F6: 0.0305 | G6: 0.0372 | H6: =Inputs!$B$26 -> 0.01775 | I6: =IF(E6>H6,"YES","no") -> no | J6: =(E6-H6)*100 -> -1.005 | K6: =(F6-H6)*100 -> 1.275
A7: SA/IN | B7: Saudi Arabia | C7: India | D7: 12 | E7: 0.0314 | F7: 0.0357 | G7: 0.0559 | H7: =Inputs!$B$26 -> 0.01775 | I7: =IF(E7>H7,"YES","no") -> YES | J7: =(E7-H7)*100 -> 1.365 | K7: =(F7-H7)*100 -> 1.795
A8: US/IN | B8: USA | C8: India | D8: 46 | E8: -0.0053 | F8: 0.0276 | G8: 0.0368 | H8: =Inputs!$B$26 -> 0.01775 | I8: =IF(E8>H8,"YES","no") -> no | J8: =(E8-H8)*100 -> -2.305 | K8: =(F8-H8)*100 -> 0.985
A9: GB/IN | B9: UK | C9: India | D9: 28 | E9: 0.0015 | F9: 0.0211 | G9: 0.0191 | H9: =Inputs!$B$26 -> 0.01775 | I9: =IF(E9>H9,"YES","no") -> no | J9: =(E9-H9)*100 -> -1.625 | K9: =(F9-H9)*100 -> 0.335
A10: US/MX | B10: USA | C10: Mexico | D10: 46 | E10: -0.0244 | F10: 0.046 | G10: 0.0454 | H10: =Inputs!$B$26 -> 0.01775 | I10: =IF(E10>H10,"YES","no") -> no | J10: =(E10-H10)*100 -> -4.215 | K10: =(F10-H10)*100 -> 2.825
A11: US/PH | B11: USA | C11: Philippines | D11: 58 | E11: 0.0058 | F11: 0.0399 | G11: 0.0452 | H11: =Inputs!$B$26 -> 0.01775 | I11: =IF(E11>H11,"YES","no") -> no | J11: =(E11-H11)*100 -> -1.195 | K11: =(F11-H11)*100 -> 2.215
A12: AE/PH | B12: UAE | C12: Philippines | D12: 21 | E12: 0.0081 | F12: 0.0343 | G12: 0.0304 | H12: =Inputs!$B$26 -> 0.01775 | I12: =IF(E12>H12,"YES","no") -> no | J12: =(E12-H12)*100 -> -0.965 | K12: =(F12-H12)*100 -> 1.655
A13: SA/PH | B13: Saudi Arabia | C13: Philippines | D13: 10 | E13: 0.0256 | F13: 0.0276 | G13: 0.0382 | H13: =Inputs!$B$26 -> 0.01775 | I13: =IF(E13>H13,"YES","no") -> YES | J13: =(E13-H13)*100 -> 0.785 | K13: =(F13-H13)*100 -> 0.985
... A36: AU/FJ | B36: Australia | C36: Fiji | D36: 26 | E36: -0.0317 | F36: 0.0369 | G36: 0.0435 | H36: =Inputs!$B$26 -> 0.01775 | I36: =IF(E36>H36,"YES","no") -> no | J36: =(E36-H36)*100 -> -4.945 | K36: =(F36-H36)*100 -> 1.915
A38: Corridors where rail beats the CHEAPEST offer | E38: =COUNTIF(I2:I36,"YES") -> 11
A39: Corridors where rail beats the MEDIAN offer | E39: =SUMPRODUCT(--(F2:F36>H2:H36)) -> 33
A40: Source: World Bank Remittance Prices Worldwide, Q3 2025 corridor pages (latest release); cost of sending $200.

Sheet Pakistan
A1: Corridor | B1: Flow FY26 ($bn) | C1: Average offer % | D1: Median offer % | E1: Cheapest offer % | F1: Rail cost % | G1: Saving vs average ($m) | H1: Saving vs median ($m) | I1: Saving vs cheapest ($m)
A2: Saudi Arabia → Pakistan | B2: =Inputs!$B$12 -> 9.78 | C2: =Corridors!G3 -> 0.0502 | D2: =Corridors!F3 -> 0.0306 | E2: =Corridors!E3 -> 0.0144 | F2: =Inputs!$B$26 -> 0.01775 | G2: =MAX(0,B2*1000*(C2-F2)) -> 317.361 | H2: =MAX(0,B2*1000*(D2-F2)) -> 125.673 | I2: =MAX(0,B2*1000*(E2-F2)) -> 0
A3: UAE → Pakistan | B3: =Inputs!$B$13 -> 8.81 | C3: =Corridors!G2 -> 0.0217 | D3: =Corridors!F2 -> 0.0063 | E3: =Corridors!E2 -> -0.0049 | F3: =Inputs!$B$26 -> 0.01775 | G3: =MAX(0,B3*1000*(C3-F3)) -> 34.7995 | H3: =MAX(0,B3*1000*(D3-F3)) -> 0 | I3: =MAX(0,B3*1000*(E3-F3)) -> 0
A4: UK → Pakistan | B4: =Inputs!$B$14 -> 6.33 | C4: =Corridors!G4 -> 0.0239 | D4: =Corridors!F4 -> 0.0251 | E4: =Corridors!E4 -> -0.0144 | F4: =Inputs!$B$26 -> 0.01775 | G4: =MAX(0,B4*1000*(C4-F4)) -> 38.9295 | H4: =MAX(0,B4*1000*(D4-F4)) -> 46.5255 | I4: =MAX(0,B4*1000*(E4-F4)) -> 0
A5: Total | B5: =SUM(B2:B4) -> 24.92 | G5: =SUM(G2:G4) -> 391.09 | H5: =SUM(H2:H4) -> 172.1985 | I5: =SUM(I2:I4) -> 0
A7: PVARA claim (Aug 2026): ~$400m/yr from a 1pp cost cut on ~$40bn flows
A8: Upper bounds: assumes 100% switching and $200-ticket pricing (larger transfers are cheaper in % terms).

Sheet Issuer P&L
A1: $m unless stated | B1: Today | C1: -25bp | D1: -50bp | E1: -100bp | F1: -150bp
A2: Rate change | B2: 0 | C2: -0.0025 | D2: -0.005 | E2: -0.01 | F2: -0.015
A3: Reserve yield | B3: =Inputs!$B$7+B2 -> 0.0394 | C3: =Inputs!$B$7+C2 -> 0.0369 | D3: =Inputs!$B$7+D2 -> 0.0344 | E3: =Inputs!$B$7+E2 -> 0.0294 | F3: =Inputs!$B$7+F2 -> 0.0244
A4: Average USDC ($bn) | B4: =Inputs!$B$6 -> 73 | C4: =Inputs!$B$6 -> 73 | D4: =Inputs!$B$6 -> 73 | E4: =Inputs!$B$6 -> 73 | F4: =Inputs!$B$6 -> 73
A5: Reserve income | B5: =B4*1000*B3 -> 2876.2 | C5: =C4*1000*C3 -> 2693.7 | D5: =D4*1000*D3 -> 2511.2 | E5: =E4*1000*E3 -> 2146.2 | F5: =F4*1000*F3 -> 1781.2
A6: Other revenue | B6: =Inputs!$B$9 -> 160 | C6: =Inputs!$B$9 -> 160 | D6: =Inputs!$B$9 -> 160 | E6: =Inputs!$B$9 -> 160 | F6: =Inputs!$B$9 -> 160
A7: Total revenue | B7: =B5+B6 -> 3036.2 | C7: =C5+C6 -> 2853.7 | D7: =D5+D6 -> 2671.2 | E7: =E5+E6 -> 2306.2 | F7: =F5+F6 -> 1941.2
A8: Distribution & transaction costs | B8: =-B5*Inputs!$B$8 -> -1740.101 | C8: =-C5*Inputs!$B$8 -> -1629.6885 | D8: =-D5*Inputs!$B$8 -> -1519.276 | E8: =-E5*Inputs!$B$8 -> -1298.451 | F8: =-F5*Inputs!$B$8 -> -1077.626
A9: Revenue less distribution (RLDC) | B9: =B7+B8 -> 1296.099 | C9: =C7+C8 -> 1224.0115 | D9: =D7+D8 -> 1151.924 | E9: =E7+E8 -> 1007.749 | F9: =F7+F8 -> 863.574
A10: RLDC margin | B10: =IF(B7=0,0,B9/B7) -> 0.42688196 | C10: =IF(C7=0,0,C9/C7) -> 0.42892087 | D10: =IF(D7=0,0,D9/D7) -> 0.43123839 | E10: =IF(E7=0,0,E9/E7) -> 0.43697381 | F10: =IF(F7=0,0,F9/F7) -> 0.44486606
A11: Adjusted opex | B11: =-Inputs!$B$10 -> -578 | C11: =-Inputs!$B$10 -> -578 | D11: =-Inputs!$B$10 -> -578 | E11: =-Inputs!$B$10 -> -578 | F11: =-Inputs!$B$10 -> -578
A12: Adjusted EBITDA | B12: =B9+B11 -> 718.099 | C12: =C9+C11 -> 646.0115 | D12: =D9+D11 -> 573.924 | E12: =E9+E11 -> 429.749 | F12: =F9+F11 -> 285.574
A13: EBITDA lost vs today | B13: =$B$12-B12 -> 0 | C13: =$B$12-C12 -> 72.0875 | D13: =$B$12-D12 -> 144.175 | E13: =$B$12-E12 -> 288.35 | F13: =$B$12-F12 -> 432.525
A14: Payment volume needed to replace lost EBITDA ($bn) | B14: =B13/Inputs!$B$11/1000 -> 0 | C14: =C13/Inputs!$B$11/1000 -> 72.0875 | D14: =D13/Inputs!$B$11/1000 -> 144.175 | E14: =E13/Inputs!$B$11/1000 -> 288.35 | F14: =F13/Inputs!$B$11/1000 -> 432.525
A16: Reading: distribution partners take ~60% of reserve income, so every 100bp of rate cuts removes ~$730m of reserve income and ~$290m of RLDC.
A17: To replace that from payments at a 10bp take rate, an issuer needs ~$290bn/yr of payment volume, about 40% of all remittances to developing countries ($685bn).
A18: Note: distribution costs are modelled as a share of reserve income (simplification). Calibrated to Circle FY2025/Q2 2026 results.

Sheet Issuer Sensitivity
A1: Adjusted EBITDA ($m): average supply (rows) × reserve yield (columns)
B2: 0.02 | C2: 0.025 | D2: 0.03 | E2: 0.035 | F2: 0.04 | G2: 0.045 | H2: 0.05
A3: 50 | B3: =$A3*1000*B$2*(1-Inputs!$B$8)+Inputs!$B$9-Inputs!$B$10 -> -23 | C3: =$A3*1000*C$2*(1-Inputs!$B$8)+Inputs!$B$9-Inputs!$B$10 -> 75.75 | D3: =$A3*1000*D$2*(1-Inputs!$B$8)+Inputs!$B$9-Inputs!$B$10 -> 174.5 | E3: =$A3*1000*E$2*(1-Inputs!$B$8)+Inputs!$B$9-Inputs!$B$10 -> 273.25 | F3: =$A3*1000*F$2*(1-Inputs!$B$8)+Inputs!$B$9-Inputs!$B$10 -> 372 | G3: =$A3*1000*G$2*(1-Inputs!$B$8)+Inputs!$B$9-Inputs!$B$10 -> 470.75 | H3: =$A3*1000*H$2*(1-Inputs!$B$8)+Inputs!$B$9-Inputs!$B$10 -> 569.5
A4: 60 | B4: =$A4*1000*B$2*(1-Inputs!$B$8)+Inputs!$B$9-Inputs!$B$10 -> 56 | C4: =$A4*1000*C$2*(1-Inputs!$B$8)+Inputs!$B$9-Inputs!$B$10 -> 174.5 | D4: =$A4*1000*D$2*(1-Inputs!$B$8)+Inputs!$B$9-Inputs!$B$10 -> 293 | E4: =$A4*1000*E$2*(1-Inputs!$B$8)+Inputs!$B$9-Inputs!$B$10 -> 411.5 | F4: =$A4*1000*F$2*(1-Inputs!$B$8)+Inputs!$B$9-Inputs!$B$10 -> 530 | G4: =$A4*1000*G$2*(1-Inputs!$B$8)+Inputs!$B$9-Inputs!$B$10 -> 648.5 | H4: =$A4*1000*H$2*(1-Inputs!$B$8)+Inputs!$B$9-Inputs!$B$10 -> 767
A5: 73 | B5: =$A5*1000*B$2*(1-Inputs!$B$8)+Inputs!$B$9-Inputs!$B$10 -> 158.7 | C5: =$A5*1000*C$2*(1-Inputs!$B$8)+Inputs!$B$9-Inputs!$B$10 -> 302.875 | D5: =$A5*1000*D$2*(1-Inputs!$B$8)+Inputs!$B$9-Inputs!$B$10 -> 447.05 | E5: =$A5*1000*E$2*(1-Inputs!$B$8)+Inputs!$B$9-Inputs!$B$10 -> 591.225 | F5: =$A5*1000*F$2*(1-Inputs!$B$8)+Inputs!$B$9-Inputs!$B$10 -> 735.4 | G5: =$A5*1000*G$2*(1-Inputs!$B$8)+Inputs!$B$9-Inputs!$B$10 -> 879.575 | H5: =$A5*1000*H$2*(1-Inputs!$B$8)+Inputs!$B$9-Inputs!$B$10 -> 1023.75
A6: 90 | B6: =$A6*1000*B$2*(1-Inputs!$B$8)+Inputs!$B$9-Inputs!$B$10 -> 293 | C6: =$A6*1000*C$2*(1-Inputs!$B$8)+Inputs!$B$9-Inputs!$B$10 -> 470.75 | D6: =$A6*1000*D$2*(1-Inputs!$B$8)+Inputs!$B$9-Inputs!$B$10 -> 648.5 | E6: =$A6*1000*E$2*(1-Inputs!$B$8)+Inputs!$B$9-Inputs!$B$10 -> 826.25 | F6: =$A6*1000*F$2*(1-Inputs!$B$8)+Inputs!$B$9-Inputs!$B$10 -> 1004 | G6: =$A6*1000*G$2*(1-Inputs!$B$8)+Inputs!$B$9-Inputs!$B$10 -> 1181.75 | H6: =$A6*1000*H$2*(1-Inputs!$B$8)+Inputs!$B$9-Inputs!$B$10 -> 1359.5
A7: 110 | B7: =$A7*1000*B$2*(1-Inputs!$B$8)+Inputs!$B$9-Inputs!$B$10 -> 451 | C7: =$A7*1000*C$2*(1-Inputs!$B$8)+Inputs!$B$9-Inputs!$B$10 -> 668.25 | D7: =$A7*1000*D$2*(1-Inputs!$B$8)+Inputs!$B$9-Inputs!$B$10 -> 885.5 | E7: =$A7*1000*E$2*(1-Inputs!$B$8)+Inputs!$B$9-Inputs!$B$10 -> 1102.75 | F7: =$A7*1000*F$2*(1-Inputs!$B$8)+Inputs!$B$9-Inputs!$B$10 -> 1320 | G7: =$A7*1000*G$2*(1-Inputs!$B$8)+Inputs!$B$9-Inputs!$B$10 -> 1537.25 | H7: =$A7*1000*H$2*(1-Inputs!$B$8)+Inputs!$B$9-Inputs!$B$10 -> 1754.5
A8: 150 | B8: =$A8*1000*B$2*(1-Inputs!$B$8)+Inputs!$B$9-Inputs!$B$10 -> 767 | C8: =$A8*1000*C$2*(1-Inputs!$B$8)+Inputs!$B$9-Inputs!$B$10 -> 1063.25 | D8: =$A8*1000*D$2*(1-Inputs!$B$8)+Inputs!$B$9-Inputs!$B$10 -> 1359.5 | E8: =$A8*1000*E$2*(1-Inputs!$B$8)+Inputs!$B$9-Inputs!$B$10 -> 1655.75 | F8: =$A8*1000*F$2*(1-Inputs!$B$8)+Inputs!$B$9-Inputs!$B$10 -> 1952 | G8: =$A8*1000*G$2*(1-Inputs!$B$8)+Inputs!$B$9-Inputs!$B$10 -> 2248.25 | H8: =$A8*1000*H$2*(1-Inputs!$B$8)+Inputs!$B$9-Inputs!$B$10 -> 2544.5
A9: 200 | B9: =$A9*1000*B$2*(1-Inputs!$B$8)+Inputs!$B$9-Inputs!$B$10 -> 1162 | C9: =$A9*1000*C$2*(1-Inputs!$B$8)+Inputs!$B$9-Inputs!$B$10 -> 1557 | D9: =$A9*1000*D$2*(1-Inputs!$B$8)+Inputs!$B$9-Inputs!$B$10 -> 1952 | E9: =$A9*1000*E$2*(1-Inputs!$B$8)+Inputs!$B$9-Inputs!$B$10 -> 2347 | F9: =$A9*1000*F$2*(1-Inputs!$B$8)+Inputs!$B$9-Inputs!$B$10 -> 2742 | G9: =$A9*1000*G$2*(1-Inputs!$B$8)+Inputs!$B$9-Inputs!$B$10 -> 3137 | H9: =$A9*1000*H$2*(1-Inputs!$B$8)+Inputs!$B$9-Inputs!$B$10 -> 3532

Sheet Corridor Product
A1: Saudi Arabia → South Asia stablecoin remittance product — 5-year P&L ($m unless stated)
A3: Line | B3: Y1 | C3: Y2 | D3: Y3 | E3: Y4 | F3: Y5
A4: New users | B4: =Inputs!$B$18 -> 40000 | C4: =B4*(1+Inputs!$B$19) -> 64000 | D4: =C4*(1+Inputs!$B$19) -> 102400 | E4: =D4*(1+Inputs!$B$19) -> 163840 | F4: =E4*(1+Inputs!$B$19) -> 262144
A5: Users retained at year end | B5: =B4*(1-Inputs!$B$20)^12 -> 24508.39 | C5: =(B5+C4)*(1-Inputs!$B$20)^12 -> 54229.954 | D5: =(C5+D4)*(1-Inputs!$B$20)^12 -> 95968.701 | E5: =(D5+E4)*(1-Inputs!$B$20)^12 -> 159187.33 | F5: =(E5+F4)*(1-Inputs!$B$20)^12 -> 258153.81
A6: Average active users | B6: =(B4+B5)/2 -> 32254.195 | C6: =(B5+C4+C5)/2 -> 71369.172 | D6: =(C5+D4+D5)/2 -> 126299.33 | E6: =(D5+E4+E5)/2 -> 209498.01 | F6: =(E5+F4+F5)/2 -> 339742.57
A7: Transfers (m) | B7: =B6*Inputs!$B$17*12/1000000 -> 0.50316544 | C7: =C6*Inputs!$B$17*12/1000000 -> 1.1133591 | D7: =D6*Inputs!$B$17*12/1000000 -> 1.9702695 | E7: =E6*Inputs!$B$17*12/1000000 -> 3.268169 | F7: =F6*Inputs!$B$17*12/1000000 -> 5.2999841
A8: Volume ($m) | B8: =B7*Inputs!$B$16 -> 150.94963 | C8: =C7*Inputs!$B$16 -> 334.00773 | D8: =D7*Inputs!$B$16 -> 591.08085 | E8: =E7*Inputs!$B$16 -> 980.4507 | F8: =F7*Inputs!$B$16 -> 1589.9952
A9: Revenue ($m) | B9: =B8*Inputs!$B$15 -> 4.0756401 | C9: =C8*Inputs!$B$15 -> 9.0182086 | D9: =D8*Inputs!$B$15 -> 15.959183 | E9: =E8*Inputs!$B$15 -> 26.472169 | F9: =F8*Inputs!$B$15 -> 42.929871
A10: Rail cost ($m) | B10: =-(B8*(Inputs!$B$2+Inputs!$B$3)+B7*Inputs!$B$4) -> -2.5409855 | C10: =-(C8*(Inputs!$B$2+Inputs!$B$3)+C7*Inputs!$B$4) -> -5.6224634 | D10: =-(D8*(Inputs!$B$2+Inputs!$B$3)+D7*Inputs!$B$4) -> -9.949861 | E10: =-(E8*(Inputs!$B$2+Inputs!$B$3)+E7*Inputs!$B$4) -> -16.504254 | F10: =-(F8*(Inputs!$B$2+Inputs!$B$3)+F7*Inputs!$B$4) -> -26.76492
A11: Contribution ($m) | B11: =B9+B10 -> 1.5346546 | C11: =C9+C10 -> 3.3957452 | D11: =D9+D10 -> 6.009322 | E11: =E9+E10 -> 9.9679155 | F11: =F9+F10 -> 16.164952
A12: Contribution margin | B12: =IF(B9=0,0,B11/B9) -> 0.37654321 | C12: =IF(C9=0,0,C11/C9) -> 0.37654321 | D12: =IF(D9=0,0,D11/D9) -> 0.37654321 | E12: =IF(E9=0,0,E11/E9) -> 0.37654321 | F12: =IF(F9=0,0,F11/F9) -> 0.37654321
A13: Acquisition spend ($m) | B13: =-B4*Inputs!$B$21/1000000 -> -0.88 | C13: =-C4*Inputs!$B$21/1000000 -> -1.408 | D13: =-D4*Inputs!$B$21/1000000 -> -2.2528 | E13: =-E4*Inputs!$B$21/1000000 -> -3.60448 | F13: =-F4*Inputs!$B$21/1000000 -> -5.767168
A14: Fixed opex ($m) | B14: =-Inputs!$B$22*(1+Inputs!$B$23)^(0) -> -3.5 | C14: =-Inputs!$B$22*(1+Inputs!$B$23)^(1) -> -4.375 | D14: =-Inputs!$B$22*(1+Inputs!$B$23)^(2) -> -5.46875 | E14: =-Inputs!$B$22*(1+Inputs!$B$23)^(3) -> -6.8359375 | F14: =-Inputs!$B$22*(1+Inputs!$B$23)^(4) -> -8.5449219
A15: EBITDA ($m) | B15: =B11+B13+B14 -> -2.8453454 | C15: =C11+C13+C14 -> -2.3872548 | D15: =D11+D13+D14 -> -1.712228 | E15: =E11+E13+E14 -> -0.472502 | F15: =F11+F13+F14 -> 1.8528616
A16: Discount factor | B16: =1/(1+Inputs!$B$24)^1 -> 0.84745763 | C16: =1/(1+Inputs!$B$24)^2 -> 0.71818443 | D16: =1/(1+Inputs!$B$24)^3 -> 0.60863087 | E16: =1/(1+Inputs!$B$24)^4 -> 0.51578888 | F16: =1/(1+Inputs!$B$24)^5 -> 0.43710922
A17: PV of EBITDA ($m) | B17: =B15*B16 -> -2.4113097 | C17: =C15*C16 -> -1.7144892 | D17: =D15*D16 -> -1.0421148 | E17: =E15*E16 -> -0.24371128 | F17: =F15*F16 -> 0.8099029
A19: NPV of 5-year EBITDA ($m) | B19: =SUM(B17:F17) -> -4.6017221
A20: Contribution per transfer ($) | B20: =Inputs!$B$16*(Inputs!$B$15-Inputs!$B$2-Inputs!$B$3)-Inputs!$B$4 -> 3.05
A21: Months of contribution to pay back CAC | B21: =IF(B20<=0,"never",Inputs!$B$21/(B20*Inputs!$B$17)) -> 5.5485498
A22: Customer saving vs cheapest Saudi→Bangladesh offer (7.15%), per $300 transfer ($) | B22: =Inputs!$B$16*(0.0715-Inputs!$B$15) -> 13.35
